multiprocess_profiler/__init__.py
multiprocess_profiler/profiler.py
multiprocess_profiler-1.0.dist-info/LICENSE.txt
multiprocess_profiler-1.0.dist-info/METADATA
multiprocess_profiler-1.0.dist-info/WHEEL
multiprocess_profiler-1.0.dist-info/top_level.txt
multiprocess_profiler-1.0.dist-info/RECORD
