Metadata-Version: 2.1
Name: multiprocess-profiler
Version: 1.0
Summary: Profile your code, measuring times, calls per function, errors...
Home-page: https://github.com/12pedro07/multiprocess_profiler
Download-URL: https://github.com/12pedro07/multiprocess_profiler/archive/refs/tags/v_01.tar.gz
Author: Pedro Henrique Silva Domingues
Author-email: 12pedro07@gmail.com
License: MIT
Keywords: Time,Profiler,Multiprocess,Multithread
Platform: UNKNOWN
Classifier: Development Status :: 3 - Alpha
Classifier: Intended Audience :: Developers
Classifier: Topic :: Software Development :: Build Tools
Classifier: License :: OSI Approved :: MIT License
Classifier: Programming Language :: Python :: 3
Classifier: Programming Language :: Python :: 3.5
Classifier: Programming Language :: Python :: 3.6
Classifier: Programming Language :: Python :: 3.7
License-File: LICENSE.txt
Requires-Dist: psutil
Requires-Dist: pathlib
Requires-Dist: filelock
Requires-Dist: typing ; python_version < "3.5"
